README.rst
setup.py
amazon_scraper/__init__.py
amazon_scraper/product.py
amazon_scraper/review.py
amazon_scraper/reviews.py
amazon_scraper/user_reviews.py
amazon_scraper/version.py
amazon_scraper.egg-info/PKG-INFO
amazon_scraper.egg-info/SOURCES.txt
amazon_scraper.egg-info/dependency_links.txt
amazon_scraper.egg-info/requires.txt
amazon_scraper.egg-info/top_level.txt