Metadata-Version: 1.1
Name: amazon-scraper
Version: 0.3.3
Summary: Provides content not accessible through the standard Amazon API
Home-page: https://github.com/adamlwgriffiths/amazon_scraper
Author: Adam Griffiths
Author-email: UNKNOWN
License: BSD
Platform: any
Classifier: Natural Language :: English
Classifier: Intended Audience :: Developers
Classifier: Operating System :: MacOS :: MacOS X
Classifier: Operating System :: Microsoft :: Windows
Classifier: Operating System :: POSIX
Classifier: Programming Language :: Python
Classifier: License :: OSI Approved :: BSD License
Classifier: Topic :: Software Development :: Libraries
Classifier: Topic :: Software Development :: Libraries :: Python Modules
Classifier: Topic :: Internet
